setup.py
nemo_annotator_plugin/__init__.py
nemo_annotator_plugin.egg-info/PKG-INFO
nemo_annotator_plugin.egg-info/SOURCES.txt
nemo_annotator_plugin.egg-info/dependency_links.txt
nemo_annotator_plugin.egg-info/not-zip-safe
nemo_annotator_plugin.egg-info/requires.txt
nemo_annotator_plugin.egg-info/top_level.txt